bm_video_tools/__init__.py
bm_video_tools/audio.py
bm_video_tools/error.py
bm_video_tools/image.py
bm_video_tools/operate.py
bm_video_tools/video.py
bm_video_tools/clips/__init__.py
bm_video_tools/clips/audio_clip.py
bm_video_tools/clips/audio_reader.py
bm_video_tools/clips/ffmpeg_reader.py
bm_video_tools/clips/video_clip.py
bm_video_tools/clips/video_reader.py
bm_video_tools/detection/__init__.py
bm_video_tools/detection/face_detection_image.py
bm_video_tools/detection/face_detection_video.py
bm_video_tools/detection/model.py
bm_video_tools/remover/__init__.py
bm_video_tools/remover/data_loader.py
bm_video_tools/remover/net.py
bm_video_tools/remover/transparent_image.py
bm_video_tools/remover/transparent_video.py
bm_video_tools/remover/u2net.py
bm_video_tools/utils/__init__.py
bm_video_tools/utils/async_utils.py
bm_video_tools/utils/sync_utils.py
bm_video_tools/utils/utils.py
tests/__init__.py
tests/test_audio.py
tests/test_image.py
tests/test_source.py
tests/test_video.py
bm_video_tools-0.1.6.dist-info/LICENSE
bm_video_tools-0.1.6.dist-info/METADATA
bm_video_tools-0.1.6.dist-info/WHEEL
bm_video_tools-0.1.6.dist-info/top_level.txt
bm_video_tools-0.1.6.dist-info/RECORD
