Metadata-Version: 2.1
Name: bm-video-tools
Version: 0.1.6
Summary: 音视频处理工具
Author: galaxyeye
Author-email: galaxyeye.wechat@galaxyeye-tech.com
Classifier: Programming Language :: Python :: 3.8
Classifier: License :: OSI Approved :: MIT License
Classifier: Operating System :: OS Independent
Requires-Python: >=3.8
License-File: LICENSE
Requires-Dist: numpy ~=1.24.4
Requires-Dist: scikit-image ~=0.21.0
Requires-Dist: pillow ~=10.0.1
Requires-Dist: moviepy ~=1.0.3
Requires-Dist: opencv-python-headless ~=4.8.1.78
Requires-Dist: torch ~=2.0.1
Requires-Dist: torchvision ~=0.15.2
